{
  "state": "FL",
  "fips5": "12005",
  "adminarea": "Bay",
  "urlvbmdropboxes": "https://www.bayvotes.org/Election-Info/Early-Voting-Sites",
  "urlearlyvoting": 0,
  "urlstatelevelvbm": "https://dos.myflorida.com/elections/for-voters/voting/vote-by-mail/",
  "flagboxes": 1,
  "areadatacode": 1,
  "arealeveltext": "Your county has Vote-By-Mail ballot dropoff ONLY at all Super Voting locations. The Show Drop-Off Options button will take you to your county webpage showing a list of Super Voting locations and dropbox hours.",
  "flagattn": 1,
  "shortname": "bay"
}