{
  "state": "TX",
  "fips5": "48041",
  "adminarea": "Brazos",
  "urlvbmdropboxes": "http://www.brazosvotes.org/node/22",
  "urlearlyvoting": "http://www.brazosvotes.org/node/197",
  "urlstatelevelvbm": "https://www.votetexas.gov/voting/when.html#early-voting",
  "flagboxes": 0,
  "areadatacode": "003",
  "arealeveltext": "Your county DOES NOT have ballot dropboxes. The SHOW DROP-OFF OPTIONS button will take you to the county webpage which shows the address for your County Election office, where you can hand deliver your completed ballot.",
  "shortname": "brazos"
}